odoo/addons/website_sale_payment_term_acquirer/README.rst
odoo/addons/website_sale_payment_term_acquirer/__init__.py
odoo/addons/website_sale_payment_term_acquirer/__manifest__.py
odoo/addons/website_sale_payment_term_acquirer/controllers/__init__.py
odoo/addons/website_sale_payment_term_acquirer/controllers/main.py
odoo/addons/website_sale_payment_term_acquirer/demo/demo.xml
odoo/addons/website_sale_payment_term_acquirer/i18n/it.po
odoo/addons/website_sale_payment_term_acquirer/i18n/website_sale_payment_term_acquirer.pot
odoo/addons/website_sale_payment_term_acquirer/models/__init__.py
odoo/addons/website_sale_payment_term_acquirer/models/payment_acquirer.py
odoo/addons/website_sale_payment_term_acquirer/models/sale_order.py
odoo/addons/website_sale_payment_term_acquirer/readme/CONTRIBUTORS.rst
odoo/addons/website_sale_payment_term_acquirer/readme/DESCRIPTION.rst
odoo/addons/website_sale_payment_term_acquirer/readme/USAGE.rst
odoo/addons/website_sale_payment_term_acquirer/static/description/icon.png
odoo/addons/website_sale_payment_term_acquirer/static/description/index.html
odoo/addons/website_sale_payment_term_acquirer/tests/__init__.py
odoo/addons/website_sale_payment_term_acquirer/tests/test_sale_order.py
odoo/addons/website_sale_payment_term_acquirer/tests/test_website_sale.py
odoo/addons/website_sale_payment_term_acquirer/views/payment_acquirer_views.xml
odoo/addons/website_sale_payment_term_acquirer/views/payment_templates.xml
odoo14_addon_website_sale_payment_term_acquirer-14.0.1.0.1.dist-info/METADATA
odoo14_addon_website_sale_payment_term_acquirer-14.0.1.0.1.dist-info/WHEEL
odoo14_addon_website_sale_payment_term_acquirer-14.0.1.0.1.dist-info/top_level.txt
odoo14_addon_website_sale_payment_term_acquirer-14.0.1.0.1.dist-info/RECORD
